lib1/__init__.py
lib1/__main__.py
lib1/app.py
lib1/cli.py
01d61084_d29e_11e9_96d1_7c5cf84ffe8e-0.1.0.dist-info/entry_points.txt
01d61084_d29e_11e9_96d1_7c5cf84ffe8e-0.1.0.dist-info/LICENSE
01d61084_d29e_11e9_96d1_7c5cf84ffe8e-0.1.0.dist-info/WHEEL
01d61084_d29e_11e9_96d1_7c5cf84ffe8e-0.1.0.dist-info/METADATA
01d61084_d29e_11e9_96d1_7c5cf84ffe8e-0.1.0.dist-info/RECORD
