Metadata-Version: 2.1
Name: 01d61084-d29e-11e9-96d1-7c5cf84ffe8e
Version: 0.1.0
Summary: 
Author: retool
Author-email: email@example.com
Requires-Python: >=3.7,<4.0
Classifier: Programming Language :: Python :: 3
Classifier: Programming Language :: Python :: 3.7
Provides-Extra: docs
Requires-Dist: attrs (==19.1.0)
Requires-Dist: click (==7.0)
